attr-stubs/METADATA.toml
attr-stubs/__init__.pyi
attr-stubs/_version_info.pyi
attr-stubs/converters.pyi
attr-stubs/exceptions.pyi
attr-stubs/filters.pyi
attr-stubs/validators.pyi
types_attrs-19.1.0.dist-info/METADATA
types_attrs-19.1.0.dist-info/WHEEL
types_attrs-19.1.0.dist-info/top_level.txt
types_attrs-19.1.0.dist-info/RECORD
