Metadata-Version: 2.1
Name: types-attrs
Version: 19.1.0
Summary: Typing stubs for attrs
Home-page: https://github.com/python/typeshed
License: Apache-2.0 license
Platform: UNKNOWN
Classifier: License :: OSI Approved :: Apache Software License
Classifier: Typing :: Typed
